tree_sitter_objc/__init__.py
tree_sitter_objc/_binding.abi3.so
tree_sitter_objc/binding.c
tree_sitter_objc/__init__.pyi
tree_sitter_objc/py.typed
tree_sitter_objc/queries/folds.scm
tree_sitter_objc/queries/highlights.scm
tree_sitter_objc/queries/indents.scm
tree_sitter_objc/queries/injections.scm
tree_sitter_objc/queries/locals.scm
tree_sitter_objc-3.0.1.dist-info/top_level.txt
tree_sitter_objc-3.0.1.dist-info/RECORD
tree_sitter_objc-3.0.1.dist-info/LICENSE
tree_sitter_objc-3.0.1.dist-info/METADATA
tree_sitter_objc-3.0.1.dist-info/WHEEL
