Metadata-Version: 2.1
Name: tree-sitter-objc
Version: 3.0.1
Summary: Objective-C grammar for tree-sitter
Author-email: Amaan Qureshi <amaanq12@gmail.com>
License: MIT
Project-URL: Homepage, https://github.com/tree-sitter-grammars/tree-sitter-objc
Keywords: incremental,parsing,tree-sitter,objc
Classifier: Intended Audience :: Developers
Classifier: Topic :: Software Development :: Compilers
Classifier: Topic :: Text Processing :: Linguistic
Classifier: Typing :: Typed
Requires-Python: >=3.9
License-File: LICENSE
Provides-Extra: core
Requires-Dist: tree-sitter~=0.22; extra == "core"
